spsdk_pemicro/__init__.py
spsdk_pemicro/probe.py
spsdk_pemicro/__pyinstaller/__init__.py
spsdk_pemicro/__pyinstaller/hook-spsdk_pemicro.py
spsdk_pemicro-0.3.0.dist-info/LICENSE
spsdk_pemicro-0.3.0.dist-info/METADATA
spsdk_pemicro-0.3.0.dist-info/WHEEL
spsdk_pemicro-0.3.0.dist-info/entry_points.txt
spsdk_pemicro-0.3.0.dist-info/top_level.txt
spsdk_pemicro-0.3.0.dist-info/RECORD
